<?xml version="1.0" encoding="utf-8"?>
<XtraSerializer version="1.0" application="View">
  <property name="#LayoutVersion"></property>
  <property name="VertScrollTipFieldName"></property>
  <property name="PreviewFieldName"></property>
  <property name="GroupPanelText"></property>
  <property name="NewItemRowText"></property>
  <property name="LevelIndent">-1</property>
  <property name="PreviewIndent">-1</property>
  <property name="PreviewLineCount">-1</property>
  <property name="ScrollStyle">LiveVertScroll, LiveHorzScroll</property>
  <property name="FocusRectStyle">CellFocus</property>
  <property name="HorzScrollStep">3</property>
  <property name="ViewCaptionHeight">-1</property>
  <property name="Columns" iskey="true" value="5">
    <property name="Item1" isnull="true" iskey="true">
      <property name="Width">69</property>
      <property name="UnboundType">DateTime</property>
      <property name="Visible">true</property>
      <property name="ColumnEditName">repositoryItemDateEdit1</property>
      <property name="VisibleIndex">0</property>
      <property name="Name">colData</property>
      <property name="OptionsFilter" isnull="true" iskey="true">
        <property name="AllowFilter">false</property>
      </property>
      <property name="FieldName">Data</property>
    </property>
    <property name="Item2" isnull="true" iskey="true">
      <property name="Width">209</property>
      <property name="UnboundType">String</property>
      <property name="Visible">true</property>
      <property name="ColumnEditName"></property>
      <property name="VisibleIndex">1</property>
      <property name="Name">colHistorico</property>
      <property name="FieldName">Histórico</property>
    </property>
    <property name="Item3" isnull="true" iskey="true">
      <property name="Width">165</property>
      <property name="UnboundType">String</property>
      <property name="Visible">true</property>
      <property name="ColumnEditName"></property>
      <property name="VisibleIndex">2</property>
      <property name="Name">colObservacao</property>
      <property name="FieldName">Observação</property>
    </property>
    <property name="Item4" isnull="true" iskey="true">
      <property name="Width">91</property>
      <property name="UnboundType">Decimal</property>
      <property name="Visible">true</property>
      <property name="ColumnEditName"></property>
      <property name="VisibleIndex">3</property>
      <property name="Name">colDebito</property>
      <property name="FieldName">Débito</property>
      <property name="Summary" iskey="true" value="1">
        <property name="Item1" isnull="true" iskey="true">
          <property name="Tag" isnull="true" />
          <property name="FieldName">Débito</property>
          <property name="SummaryType">Sum</property>
          <property name="DisplayFormat">n2</property>
        </property>
      </property>
    </property>
    <property name="Item5" isnull="true" iskey="true">
      <property name="Width">97</property>
      <property name="UnboundType">Decimal</property>
      <property name="Visible">true</property>
      <property name="ColumnEditName"></property>
      <property name="VisibleIndex">4</property>
      <property name="Name">colCredito</property>
      <property name="FieldName">Crédito</property>
      <property name="Summary" iskey="true" value="1">
        <property name="Item1" isnull="true" iskey="true">
          <property name="Tag" isnull="true" />
          <property name="FieldName">Crédito</property>
          <property name="SummaryType">Sum</property>
          <property name="DisplayFormat">n2</property>
        </property>
      </property>
    </property>
  </property>
  <property name="ViewCaption"></property>
  <property name="BorderStyle">Default</property>
  <property name="SynchronizeClones">true</property>
  <property name="DetailTabHeaderLocation">Top</property>
  <property name="Name">gridControl</property>
  <property name="DetailHeight">350</property>
  <property name="Tag" isnull="true" />
  <property name="ChildGridLevelName"></property>
  <property name="GroupFormat">{0}: [#image]{1} {2}</property>
  <property name="ActiveFilterEnabled">true</property>
  <property name="GroupRowHeight">-1</property>
  <property name="FixedLineWidth">2</property>
  <property name="OptionsView" isnull="true" iskey="true">
    <property name="ShowFooter">true</property>
  </property>
  <property name="ColumnPanelRowHeight">-1</property>
  <property name="RowSeparatorHeight">0</property>
  <property name="FooterPanelHeight">-1</property>
  <property name="HorzScrollVisibility">Auto</property>
  <property name="VertScrollVisibility">Auto</property>
  <property name="RowHeight">-1</property>
  <property name="IndicatorWidth">-1</property>
  <property name="FormatRules" iskey="true" value="0" />
  <property name="ActiveFilterString"></property>
  <property name="FormatConditions" iskey="true" value="0" />
  <property name="GroupSummary" iskey="true" value="0" />
  <property name="GroupSummarySortInfoState"></property>
  <property name="FindFilterText"></property>
  <property name="FindPanelVisible">false</property>
</XtraSerializer>